qlapi/__init__.py
qlapi/ql.py
qlapi/ql_config.py
qlapi/ql_dependence.py
qlapi/ql_env.py
qlapi/ql_log.py
qlapi/ql_script.py
qlapi/ql_system.py
qlapi/ql_task.py
qinglongapi-0.0.3.dist-info/LICENSE
qinglongapi-0.0.3.dist-info/METADATA
qinglongapi-0.0.3.dist-info/WHEEL
qinglongapi-0.0.3.dist-info/top_level.txt
qinglongapi-0.0.3.dist-info/RECORD
