Metadata-Version: 2.1
Name: qinglongapi
Version: 0.0.3
Summary: 青龙面板api SDK
Home-page: https://github.com/yuxian158/qinglong-api
Author: yuxian158
Author-email: yuxian158@gmail.com
Project-URL: Bug Tracker, https://github.com/yuxian158/qinglong-api/issues
Classifier: Programming Language :: Python :: 3
Classifier: License :: OSI Approved :: MIT License
Classifier: Operating System :: OS Independent
Requires-Python: >=3.6
License-File: LICENSE
Requires-Dist: requests
